[
    {
        "condition": "minecraft:reference",
        "name": "enchantmentplus:recipes/tools/swords"
    },
    {
        "condition": "minecraft:inverted",
        "term": {
            "condition": "minecraft:location_check",
            "predicate": {
                "block": {
                    "nbt": "{Items:[{Slot:3b,tag:{Enchantments:[{id:\"minecraft:looting\",lvl:10s}]}}]}"
                }
            }
        }
    },
    {
        "condition": "minecraft:alternative",
        "terms": [
            {
                "condition": "minecraft:reference",
                "name": "enchantmentplus:recipes/vanilla/looting/looting_10"
            },
            {
                "condition": "minecraft:reference",
                "name": "enchantmentplus:recipes/vanilla/looting/looting_9"
            },
            {
                "condition": "minecraft:reference",
                "name": "enchantmentplus:recipes/vanilla/looting/looting_8"
            },
            {
                "condition": "minecraft:reference",
                "name": "enchantmentplus:recipes/vanilla/looting/looting_7"
            },
            {
                "condition": "minecraft:reference",
                "name": "enchantmentplus:recipes/vanilla/looting/looting_6"
            },
            {
                "condition": "minecraft:reference",
                "name": "enchantmentplus:recipes/vanilla/looting/looting_5"
            },
            {
                "condition": "minecraft:reference",
                "name": "enchantmentplus:recipes/vanilla/looting/looting_4"
            },
            {
                "condition": "minecraft:reference",
                "name": "enchantmentplus:recipes/vanilla/looting/looting_3"
            }
        ]
    }
]